selenium_elements/__init__.py
selenium_elements/conditions.py
selenium_elements/elements.py
selenium_elements/page.py
selenium_elements/types.py
selenium_elements/validators.py
selenium_elements-0.0.2.dist-info/LICENSE
selenium_elements-0.0.2.dist-info/METADATA
selenium_elements-0.0.2.dist-info/WHEEL
selenium_elements-0.0.2.dist-info/top_level.txt
selenium_elements-0.0.2.dist-info/RECORD
