Metadata-Version: 2.1
Name: selenium-elements
Version: 0.0.2
Summary: Page object model made easy.
Home-page: https://github.com/danclaudiupop/selenium_elements
Author: Dan Claudiu Pop
Author-email: danclaudiupop@gmail.com
License: BSD 2-Clause License
Keywords: selenium,tests,page model
Platform: UNKNOWN
Classifier: Development Status :: 5 - Production/Stable
Classifier: Intended Audience :: Developers
Classifier: License :: OSI Approved :: BSD License
Classifier: Operating System :: Unix
Classifier: Programming Language :: Python
Classifier: Programming Language :: Python :: 3.7
Classifier: Topic :: Utilities
Requires-Python: >=3.7
Requires-Dist: selenium
